[{"Account Manager": "Eder Rodrigues", "Conclusao": 50.0, "Horas": 2, "HorasRestantes": -346.0, "Projeto": "JAMEF TRANSPORTES LTDA", "Squad": "Data e Power", "Status": "EM ATENDIMENTO", "VencimentoEm": "N/A"}, {"Account Manager": "Eder Rodrigues", "Conclusao": 0.0, "Horas": 0, "HorasRestantes": -1068.1, "Projeto": "JAMEF TRANSPORTES LTDA", "Squad": "Data e Power", "Status": "EM ATENDIMENTO", "VencimentoEm": "N/A"}, {"Account Manager": "Edison Sprandel", "Conclusao": 25.0, "Horas": 208, "HorasRestantes": 117.6, "Projeto": "STELLA - ULTRA FILIAL", "Squad": "M365", "Status": "AGUARDANDO", "VencimentoEm": "11/04/2025"}, {"Account Manager": "Junior Brevia", "Conclusao": 50.0, "Horas": 60, "HorasRestantes": -44.8, "Projeto": "NEC ENERGIA", "Squad": "M365", "Status": "AGUARDANDO", "VencimentoEm": "31/03/2025"}, {"Account Manager": "Thiago Alcantara", "Conclusao": 100.0, "Horas": 84, "HorasRestantes": -130.1, "Projeto": "ENFORCE GESTAO DE ATIVOS S.A.", "Squad": "Data e Power", "Status": "EM ATENDIMENTO", "VencimentoEm": "24/03/2025"}, {"Account Manager": "Edison Sprandel", "Conclusao": 25.0, "Horas": 34, "HorasRestantes": -65.6, "Projeto": "HAVAN", "Squad": "M365", "Status": "AGUARDANDO", "VencimentoEm": "27/12/2024"}, {"Account Manager": "Mateus Silva", "Conclusao": 75.0, "Horas": 700, "HorasRestantes": 105.2, "Projeto": "Marilan", "Squad": "Azure", "Status": "EM ATENDIMENTO", "VencimentoEm": "18/04/2025"}, {"Account Manager": "Denilson Barboza", "Conclusao": 50.0, "Horas": 80, "HorasRestantes": 64.6, "Projeto": "HT MICRON", "Squad": "M365", "Status": "AGUARDANDO", "VencimentoEm": "18/04/2025"}, {"Account Manager": "Jéssica Oliveira", "Conclusao": 75.0, "Horas": 250, "HorasRestantes": 52.6, "Projeto": "LIONS TRUST ADMINISTRADORA DE RECURSOS LTDA", "Squad": "M365", "Status": "EM ATENDIMENTO", "VencimentoEm": "31/01/2025"}, {"Account Manager": "Erika Okada", "Conclusao": 50.0, "Horas": 60, "HorasRestantes": 13.1, "Projeto": "TradersClub", "Squad": "M365", "Status": "AGUARDANDO", "VencimentoEm": "30/06/2025"}, {"Account Manager": "Eder Rodrigues", "Conclusao": 0.0, "Horas": 200, "HorasRestantes": -98.7, "Projeto": "COMERCIAL ZAFFARI (GAUCHINHO)", "Squad": "Data e Power", "Status": "EM ATENDIMENTO", "VencimentoEm": "N/A"}, {"Account Manager": "Thiago Alcantara", "Conclusao": 75.0, "Horas": 138, "HorasRestantes": -89.0, "Projeto": "ENFORCE GESTAO DE ATIVOS S.A.", "Squad": "Data e Power", "Status": "EM ATENDIMENTO", "VencimentoEm": "28/03/2025"}, {"Account Manager": "Mateus Silva", "Conclusao": 5.0, "Horas": 20, "HorasRestantes": 18.7, "Projeto": "YOSEN", "Squad": "M365", "Status": "AGUARDANDO", "VencimentoEm": "30/04/2025"}, {"Account Manager": "Edison Sprandel", "Conclusao": 0.0, "Horas": 40, "HorasRestantes": 40.0, "Projeto": "HAVAN", "Squad": "M365", "Status": "NOVO", "VencimentoEm": "N/A"}, {"Account Manager": "Gustavo Moyses", "Conclusao": 5.0, "Horas": 45, "HorasRestantes": 44.8, "Projeto": "BLB Auditores", "Squad": "M365", "Status": "EM ATENDIMENTO", "VencimentoEm": "21/04/2025"}, {"Account Manager": "Eder Rodrigues", "Conclusao": 25.0, "Horas": 495, "HorasRestantes": 352.8, "Projeto": "PROTECTING BRAINS & SAVING FUTURES SISTEMA DE DIAGNOSTICOS INTEGRADOS LTDA", "Squad": "Azure", "Status": "EM ATENDIMENTO", "VencimentoEm": "30/05/2025"}, {"Account Manager": "João Mendonça - TEEVO", "Conclusao": 0.0, "Horas": 43, "HorasRestantes": 23.0, "Projeto": "CONVERT COMPANY", "Squad": "M365", "Status": "EM ATENDIMENTO", "VencimentoEm": "02/04/2025"}, {"Account Manager": "João Mendonça - TEEVO", "Conclusao": 0.0, "Horas": 10, "HorasRestantes": 10.0, "Projeto": "CONVERT COMPANY", "Squad": "M365", "Status": "NOVO", "VencimentoEm": "N/A"}, {"Account Manager": "Erika Okada", "Conclusao": 75.0, "Horas": 90, "HorasRestantes": 74.7, "Projeto": "SISCOM", "Squad": "M365", "Status": "AGUARDANDO", "VencimentoEm": "04/04/2025"}, {"Account Manager": "Mateus Silva", "Conclusao": 5.0, "Horas": 50, "HorasRestantes": 21.5, "Projeto": "YOSEN", "Squad": "M365", "Status": "EM ATENDIMENTO", "VencimentoEm": "30/04/2025"}, {"Account Manager": "Gustavo Moyses", "Conclusao": 0.0, "Horas": 32, "HorasRestantes": 2.3, "Projeto": "IDEVER INTELIGENCIA DIGITAL LTDA", "Squad": "Azure", "Status": "EM ATENDIMENTO", "VencimentoEm": "N/A"}, {"Account Manager": "Thiago Alcantara", "Conclusao": 0.0, "Horas": 12, "HorasRestantes": 12.0, "Projeto": "CAMPOS MELLO ADVOGADOS", "Squad": "M365", "Status": "EM ATENDIMENTO", "VencimentoEm": "N/A"}, {"Account Manager": "Thiago Alcantara", "Conclusao": 0.0, "Horas": 35, "HorasRestantes": 35.0, "Projeto": "CAMPOS MELLO ADVOGADOS", "Squad": "M365", "Status": "EM ATENDIMENTO", "VencimentoEm": "N/A"}, {"Account Manager": "Thiago Alcantara", "Conclusao": 0.0, "Horas": 45, "HorasRestantes": 45.0, "Projeto": "CAMPOS MELLO ADVOGADOS", "Squad": "M365", "Status": "EM ATENDIMENTO", "VencimentoEm": "N/A"}, {"Account Manager": "Thiago Alcantara", "Conclusao": 0.0, "Horas": 40, "HorasRestantes": 40.0, "Projeto": "CAMPOS MELLO ADVOGADOS", "Squad": "M365", "Status": "EM ATENDIMENTO", "VencimentoEm": "N/A"}, {"Account Manager": "Thiago Alcantara", "Conclusao": 0.0, "Horas": 100, "HorasRestantes": 100.0, "Projeto": "CAMPOS MELLO ADVOGADOS", "Squad": "M365", "Status": "EM ATENDIMENTO", "VencimentoEm": "N/A"}, {"Account Manager": "Mateus Silva", "Conclusao": 0.0, "Horas": 150, "HorasRestantes": 150.0, "Projeto": "SUPLEY", "Squad": "Data e Power", "Status": "EM ATENDIMENTO", "VencimentoEm": "N/A"}, {"Account Manager": "Mateus Silva", "Conclusao": 0.0, "Horas": 80, "HorasRestantes": 80.0, "Projeto": "SUPLEY", "Squad": "Azure", "Status": "EM ATENDIMENTO", "VencimentoEm": "N/A"}, {"Account Manager": "Mateus Silva", "Conclusao": 0.0, "Horas": 188, "HorasRestantes": 188.0, "Projeto": "SUPLEY", "Squad": "Data e Power", "Status": "EM ATENDIMENTO", "VencimentoEm": "N/A"}, {"Account Manager": "Denilson Barboza", "Conclusao": 0.0, "Horas": 42, "HorasRestantes": 42.0, "Projeto": "NEWFIELDS BRASIL", "Squad": "M365", "Status": "NOVO", "VencimentoEm": "N/A"}, {"Account Manager": "Diogo Lima", "Conclusao": 0.0, "Horas": 10, "HorasRestantes": 10.0, "Projeto": "RECORD", "Squad": "M365", "Status": "EM ATENDIMENTO", "VencimentoEm": "12/05/2025"}, {"Account Manager": "Juliana Santos", "Conclusao": 0.0, "Horas": 22, "HorasRestantes": 22.0, "Projeto": "INSTITUTO MONITOR", "Squad": "Azure", "Status": "NOVO", "VencimentoEm": "N/A"}, {"Account Manager": "Thiago Alcantara", "Conclusao": 0.0, "Horas": 10, "HorasRestantes": 10.0, "Projeto": "ENFORCE GESTAO DE ATIVOS S.A.", "Squad": "M365", "Status": "EM ATENDIMENTO", "VencimentoEm": "12/05/2025"}, {"Account Manager": "Thiago Alcantara", "Conclusao": 0.0, "Horas": 10, "HorasRestantes": 10.0, "Projeto": "ENFORCE GESTAO DE ATIVOS S.A.", "Squad": "M365", "Status": "EM ATENDIMENTO", "VencimentoEm": "12/05/2025"}, {"Account Manager": "Erika Okada", "Conclusao": 0.0, "Horas": 10, "HorasRestantes": 10.0, "Projeto": "SICOOB CREDICERIPA", "Squad": "M365", "Status": "AGUARDANDO", "VencimentoEm": "12/05/2025"}, {"Account Manager": "Erika Okada", "Conclusao": 0.0, "Horas": 10, "HorasRestantes": 10.0, "Projeto": "SICOOB CREDICERIPA", "Squad": "M365", "Status": "AGUARDANDO", "VencimentoEm": "12/05/2025"}, {"Account Manager": "Mateus Silva", "Conclusao": 0.0, "Horas": 10, "HorasRestantes": 10.0, "Projeto": "Cerradinho", "Squad": "M365", "Status": "EM ATENDIMENTO", "VencimentoEm": "12/05/2025"}, {"Account Manager": "Mateus Silva", "Conclusao": 0.0, "Horas": 10, "HorasRestantes": 10.0, "Projeto": "Cerradinho", "Squad": "M365", "Status": "EM ATENDIMENTO", "VencimentoEm": "12/05/2025"}, {"Account Manager": "Edison Sprandel", "Conclusao": 25.0, "Horas": 10, "HorasRestantes": 6.8, "Projeto": "REDE OBA HORTIFRUTI", "Squad": "M365", "Status": "AGUARDANDO", "VencimentoEm": "12/05/2025"}, {"Account Manager": "Gustavo Moyses", "Conclusao": 5.0, "Horas": 32, "HorasRestantes": 31.8, "Projeto": "SuperFrio", "Squad": "M365", "Status": "AGUARDANDO", "VencimentoEm": "28/04/2025"}, {"Account Manager": "Juliana Santos", "Conclusao": 5.0, "Horas": 55, "HorasRestantes": 50.0, "Projeto": "GNG Fundações", "Squad": "M365", "Status": "AGUARDANDO", "VencimentoEm": "25/04/2025"}, {"Account Manager": "Denilson Barboza", "Conclusao": 25.0, "Horas": 45, "HorasRestantes": 31.8, "Projeto": "Doctor Clin Operadora de Planos de Saúde", "Squad": "M365", "Status": "AGUARDANDO", "VencimentoEm": "16/04/2025"}, {"Account Manager": "Caio D'Agostini", "Conclusao": 75.0, "Horas": 28, "HorasRestantes": -0.9, "Projeto": "Novo Cliente Projetos", "Squad": "M365", "Status": "AGUARDANDO", "VencimentoEm": "15/04/2025"}, {"Account Manager": "Tatiana Lesnieski", "Conclusao": 0.0, "Horas": 24, "HorasRestantes": 22.0, "Projeto": "FOSNOR - GALVANI", "Squad": "Azure", "Status": "AGUARDANDO", "VencimentoEm": "N/A"}, {"Account Manager": "Gustavo Moyses", "Conclusao": 0.0, "Horas": 6, "HorasRestantes": 1.7, "Projeto": "PRO - LINHAS", "Squad": "Azure", "Status": "AGUARDANDO", "VencimentoEm": "14/04/2025"}, {"Account Manager": "Diogo Lima", "Conclusao": 50.0, "Horas": 24, "HorasRestantes": 10.6, "Projeto": "TRIUNFO", "Squad": "Azure", "Status": "EM ATENDIMENTO", "VencimentoEm": "11/04/2025"}, {"Account Manager": "Gustavo Moyses", "Conclusao": 0.0, "Horas": 8, "HorasRestantes": 5.1, "Projeto": "IPM SISTEMAS", "Squad": "Azure", "Status": "EM ATENDIMENTO", "VencimentoEm": "18/04/2025"}, {"Account Manager": "Eder Rodrigues", "Conclusao": 75.0, "Horas": 40, "HorasRestantes": 6.4, "Projeto": "BIB", "Squad": "M365", "Status": "EM ATENDIMENTO", "VencimentoEm": "31/03/2025"}, {"Account Manager": "Juliana Santos", "Conclusao": 5.0, "Horas": 201, "HorasRestantes": 172.9, "Projeto": "Novo Cliente Projetos", "Squad": "M365", "Status": "EM ATENDIMENTO", "VencimentoEm": "19/05/2025"}, {"Account Manager": "Diogo Lima", "Conclusao": 0.0, "Horas": 10, "HorasRestantes": 10.0, "Projeto": "NEOBPO", "Squad": "M365", "Status": "AGUARDANDO", "VencimentoEm": "12/05/2025"}, {"Account Manager": "Diogo Lima", "Conclusao": 0.0, "Horas": 10, "HorasRestantes": 10.0, "Projeto": "NEOBPO", "Squad": "M365", "Status": "AGUARDANDO", "VencimentoEm": "12/05/2025"}, {"Account Manager": "Cleber Bastos", "Conclusao": 0.0, "Horas": 10, "HorasRestantes": 10.0, "Projeto": "CAFÉ 3 CORAÇÕES", "Squad": "M365", "Status": "NOVO", "VencimentoEm": "12/05/2025"}, {"Account Manager": "Cleber Bastos", "Conclusao": 0.0, "Horas": 10, "HorasRestantes": 10.0, "Projeto": "CAFÉ 3 CORAÇÕES", "Squad": "M365", "Status": "NOVO", "VencimentoEm": "12/05/2025"}, {"Account Manager": "Diogo Lima", "Conclusao": 0.0, "Horas": 10, "HorasRestantes": 10.0, "Projeto": "TOZZINI FREIRE", "Squad": "M365", "Status": "NOVO", "VencimentoEm": "12/05/2025"}, {"Account Manager": "Diogo Lima", "Conclusao": 0.0, "Horas": 10, "HorasRestantes": 10.0, "Projeto": "TOZZINI FREIRE", "Squad": "M365", "Status": "NOVO", "VencimentoEm": "12/05/2025"}, {"Account Manager": "Mateus Silva", "Conclusao": 0.0, "Horas": 10, "HorasRestantes": 10.0, "Projeto": "BILD", "Squad": "M365", "Status": "EM ATENDIMENTO", "VencimentoEm": "11/05/2025"}, {"Account Manager": "Diogo Lima", "Conclusao": 0.0, "Horas": 10, "HorasRestantes": 8.0, "Projeto": "CAIXA RESIDENCIAL", "Squad": "M365", "Status": "EM ATENDIMENTO", "VencimentoEm": "25/04/2025"}, {"Account Manager": "Diogo Lima", "Conclusao": 0.0, "Horas": 10, "HorasRestantes": 8.5, "Projeto": "CAIXA RESIDENCIAL", "Squad": "M365", "Status": "EM ATENDIMENTO", "VencimentoEm": "25/04/2025"}, {"Account Manager": "Mateus Silva", "Conclusao": 5.0, "Horas": 10, "HorasRestantes": 2.0, "Projeto": "BILD", "Squad": "M365", "Status": "EM ATENDIMENTO", "VencimentoEm": "N/A"}, {"Account Manager": "Diogo Lima", "Conclusao": 0.0, "Horas": 10, "HorasRestantes": 10.0, "Projeto": "TENDA ATACADO", "Squad": "M365", "Status": "AGUARDANDO", "VencimentoEm": "12/05/2025"}, {"Account Manager": "Diogo Lima", "Conclusao": 0.0, "Horas": 10, "HorasRestantes": 10.0, "Projeto": "TENDA ATACADO", "Squad": "M365", "Status": "AGUARDANDO", "VencimentoEm": "25/04/2025"}, {"Account Manager": "Thiago Alcantara", "Conclusao": 0.0, "Horas": 10, "HorasRestantes": 9.9, "Projeto": "CAMPOS MELLO ADVOGADOS", "Squad": "Azure", "Status": "AGUARDANDO", "VencimentoEm": "N/A"}, {"Account Manager": "Thiago Alcantara", "Conclusao": 50.0, "Horas": 138, "HorasRestantes": -15.1, "Projeto": "ENFORCE GESTAO DE ATIVOS S.A.", "Squad": "Data e Power", "Status": "EM ATENDIMENTO", "VencimentoEm": "18/04/2025"}, {"Account Manager": "Gustavo Moyses", "Conclusao": 0.0, "Horas": 14, "HorasRestantes": 13.9, "Projeto": "BP One Group", "Squad": "Azure", "Status": "NOVO", "VencimentoEm": "N/A"}, {"Account Manager": "Thaise Albuquerque", "Conclusao": 0.0, "Horas": 50, "HorasRestantes": 49.9, "Projeto": "FSA SOLUCOES", "Squad": "Azure", "Status": "AGUARDANDO", "VencimentoEm": "N/A"}]